.long-description.html
README.rst
setup.py
src/collective/__init__.py
src/collective.cart.stock.egg-info/PKG-INFO
src/collective.cart.stock.egg-info/SOURCES.txt
src/collective.cart.stock.egg-info/dependency_links.txt
src/collective.cart.stock.egg-info/entry_points.txt
src/collective.cart.stock.egg-info/namespace_packages.txt
src/collective.cart.stock.egg-info/not-zip-safe
src/collective.cart.stock.egg-info/requires.txt
src/collective.cart.stock.egg-info/top_level.txt
src/collective/cart/__init__.py
src/collective/cart/stock/__init__.py
src/collective/cart/stock/configure.zcml
src/collective/cart/stock/content.py
src/collective/cart/stock/interfaces.py
src/collective/cart/stock/schema.py
src/collective/cart/stock/subscriber.py
src/collective/cart/stock/browser/__init__.py
src/collective/cart/stock/browser/configure.zcml
src/collective/cart/stock/browser/interfaces.py
src/collective/cart/stock/browser/static/stock.png
src/collective/cart/stock/docs/CONTRIBUTORS.rst
src/collective/cart/stock/docs/CREDITS.rst
src/collective/cart/stock/docs/HISTORY.rst
src/collective/cart/stock/docs/LICENSE.rst
src/collective/cart/stock/locales/collective.cart.stock.pot
src/collective/cart/stock/locales/en/LC_MESSAGES/collective.cart.stock.mo
src/collective/cart/stock/locales/en/LC_MESSAGES/collective.cart.stock.po
src/collective/cart/stock/locales/fi/LC_MESSAGES/collective.cart.stock.mo
src/collective/cart/stock/locales/fi/LC_MESSAGES/collective.cart.stock.po
src/collective/cart/stock/locales/fi/LC_MESSAGES/plone.dexterity.mo
src/collective/cart/stock/locales/fi/LC_MESSAGES/plone.dexterity.po
src/collective/cart/stock/profiles/default/browserlayer.xml
src/collective/cart/stock/profiles/default/metadata.xml
src/collective/cart/stock/profiles/default/rolemap.xml
src/collective/cart/stock/profiles/default/types.xml
src/collective/cart/stock/profiles/default/workflows.xml
src/collective/cart/stock/profiles/default/types/collective.cart.stock.Stock.xml
src/collective/cart/stock/tests/__init__.py
src/collective/cart/stock/tests/base.py
src/collective/cart/stock/tests/test_content.py
src/collective/cart/stock/tests/test_functional.py
src/collective/cart/stock/tests/test_setup.py
src/collective/cart/stock/tests/dexterity/__init__.py
src/collective/cart/stock/tests/dexterity/__init__.pyo
src/collective/cart/stock/tests/dexterity/configure.zcml
